[
  {
    "admin_name": "mentor1",
    "assigned_at": "2026-02-05T10:39:10",
    "assigned_by": 2,
    "ended_at": null,
    "id": 4,
    "learner_avatar": null,
    "learner_email": "admin1@test.com",
    "learner_id": 3,
    "learner_name": "admin1",
    "mentor_avatar": null,
    "mentor_email": "mentor1@test.com",
    "mentor_id": 2,
    "mentor_name": "mentor1",
    "mentor_online": true,
    "notes": "Auto-synced from booking #13",
    "status": "active"
  },
  {
    "admin_name": "mentor1",
    "assigned_at": "2026-02-05T03:38:01",
    "assigned_by": 2,
    "ended_at": null,
    "id": 2,
    "learner_avatar": null,
    "learner_email": "user1@test.com",
    "learner_id": 1,
    "learner_name": "Thanh Phú",
    "mentor_avatar": null,
    "mentor_email": "mentor1@test.com",
    "mentor_id": 2,
    "mentor_name": "mentor1",
    "mentor_online": true,
    "notes": "Fixed assignment",
    "status": "active"
  },
  {
    "admin_name": "mentor1",
    "assigned_at": "2026-02-05T03:38:00",
    "assigned_by": 2,
    "ended_at": null,
    "id": 1,
    "learner_avatar": null,
    "learner_email": "user03@gmail.com",
    "learner_id": 11,
    "learner_name": "Test User 2025",
    "mentor_avatar": null,
    "mentor_email": "mentor1@test.com",
    "mentor_id": 2,
    "mentor_name": "mentor1",
    "mentor_online": true,
    "notes": "Fixed assignment",
    "status": "active"
  }
]